{"table":[{"date":"08-02-1988","weekly":[],"daily":false,"intervals":[{"start":"00:00","end":"01:00"}],"id":0},{"date":"08-02-1988","weekly":[],"daily":false,"intervals":[{"start":"00:00","end":"01:00"}],"id":1},{"date":"08-02-1988","weekly":[],"daily":false,"intervals":[{"start":"00:00","end":"01:00"}],"id":2},{"date":"08-02-1988","weekly":[],"daily":false,"intervals":[{"start":"00:00","end":"01:00"}],"id":3},{"date":"08-02-1988","weekly":[],"daily":false,"intervals":[{"start":"00:00","end":"01:00"}],"id":4},{"date":"08-02-1988","weekly":[],"daily":false,"intervals":[{"start":"00:00","end":"01:00"}],"id":5}]}